currency_open_exchange/__init__.py
currency_open_exchange/admin.py
currency_open_exchange/backends.py
currency_open_exchange/exceptions.py
currency_open_exchange/models.py
currency_open_exchange/settings.py
currency_open_exchange/utils.py
currency_open_exchange/management/__init__.py
currency_open_exchange/management/commands/__init__.py
currency_open_exchange/management/commands/update_rates.py
currency_open_exchange/migrations/0001_initial.py
currency_open_exchange/migrations/__init__.py
currency_open_exchange-0.0.6.dist-info/DESCRIPTION.rst
currency_open_exchange-0.0.6.dist-info/METADATA
currency_open_exchange-0.0.6.dist-info/RECORD
currency_open_exchange-0.0.6.dist-info/WHEEL
currency_open_exchange-0.0.6.dist-info/metadata.json
currency_open_exchange-0.0.6.dist-info/top_level.txt
tests/__init__.py
tests/test_conversion.py
